tyco/__init__.py
tyco/__main__.py
tyco/_parser.py
tyco/cli.py
tyco/example.tyco
tyco/tests/__init__.py
tyco/tests/test_cli.py
tyco/tests/test_load_features.py
tyco/tests/test_parser.py
tyco-0.3.4.dist-info/licenses/LICENSE
tyco-0.3.4.dist-info/METADATA
tyco-0.3.4.dist-info/WHEEL
tyco-0.3.4.dist-info/entry_points.txt
tyco-0.3.4.dist-info/top_level.txt
tyco-0.3.4.dist-info/RECORD
